ci_msg_parser/__init__.py
ci_msg_parser/parser.py
ci_msg_parser-1.0.0.dist-info/METADATA
ci_msg_parser-1.0.0.dist-info/WHEEL
ci_msg_parser-1.0.0.dist-info/RECORD
