Metadata-Version: 2.4
Name: ci-msg-parser
Version: 1.0.0
Summary: NSRTW_mk4 MQTT protocol message parser
Project-URL: Homepage, https://github.com/BPaillard/ci-msg-parser
License-Expression: MIT
Provides-Extra: dev
Requires-Dist: build; extra == 'dev'
Requires-Dist: pytest; extra == 'dev'
Requires-Dist: twine; extra == 'dev'
